configparserext.py
configparserext-1.4.8.dist-info/LICENSE
configparserext-1.4.8.dist-info/METADATA
configparserext-1.4.8.dist-info/WHEEL
configparserext-1.4.8.dist-info/RECORD
