Metadata-Version: 2.3
Name: ConfigParserExt
Version: 1.4.8
Summary: Expansion of python configparser module.  There are much better tools than this like JSON, TOML & YAML.  Do not use this tool.
License: MIT
Author: Hendrik du Toit
Author-email: hendrik@brightedge.co.za
Requires-Python: >=3.10
Classifier: Development Status :: 7 - Inactive
Classifier: Intended Audience :: Developers
Classifier: Intended Audience :: Information Technology
Classifier: Topic :: Software Development
Classifier: Topic :: System :: Archiving :: Packaging
Classifier: License :: OSI Approved :: MIT License
Classifier: Programming Language :: Python :: 3.10
Classifier: Programming Language :: Python :: 3.11
Classifier: Programming Language :: Python :: 3.12
Requires-Dist: beetools (>=5.2.4,<6.0.0)
Project-URL: Homepage, https://github.com/BrightEdgeeServices/ConfigParserExt
Project-URL: Repository, https://github.com/BrightEdgeeServices/ConfigParserExt.git
Project-URL: changelog, https://github.com/BrightEdgeeServices/ConfigParserExt/blob/enhancement/master/ReleaseNotes.md
Project-URL: issues, https://github.com/BrightEdgeeServices/ConfigParserExt/issues
